MANIFEST.in
README.md
chinese_holiday.py
setup.cfg
setup.py
Chinese_holiday.egg-info/PKG-INFO
Chinese_holiday.egg-info/SOURCES.txt
Chinese_holiday.egg-info/dependency_links.txt
Chinese_holiday.egg-info/requires.txt
Chinese_holiday.egg-info/top_level.txt