Metadata-Version: 2.1
Name: Chinese-holiday
Version: 0.1.5
Summary: Chinese holiday for Python
Home-page: https://github.com/chariothy/Chinese-holiday.git
Author: Henry TIAN
Author-email: chariothy@gmail.com
License: MIT
Platform: UNKNOWN
Classifier: License :: OSI Approved :: MIT License
Classifier: Programming Language :: Python
Classifier: Programming Language :: Python :: 3.5
Classifier: Programming Language :: Python :: Implementation :: CPython
Requires-Python: >=3.5.0
